huaweicloudsdkapm/__init__.py
huaweicloudsdkapm/v1/__init__.py
huaweicloudsdkapm/v1/apm_async_client.py
huaweicloudsdkapm/v1/apm_client.py
huaweicloudsdkapm/v1/model/__init__.py
huaweicloudsdkapm/v1/model/access_aksk_vo.py
huaweicloudsdkapm/v1/model/access_point_model.py
huaweicloudsdkapm/v1/model/agent_delete_param.py
huaweicloudsdkapm/v1/model/agent_search_param.py
huaweicloudsdkapm/v1/model/agent_status_change_param.py
huaweicloudsdkapm/v1/model/alarm_data_list_request.py
huaweicloudsdkapm/v1/model/alarm_data_vo.py
huaweicloudsdkapm/v1/model/alarm_notify_list_request.py
huaweicloudsdkapm/v1/model/app_info.py
huaweicloudsdkapm/v1/model/app_node_model.py
huaweicloudsdkapm/v1/model/app_search_param.py
huaweicloudsdkapm/v1/model/business_env_request.py
huaweicloudsdkapm/v1/model/business_node_model.py
huaweicloudsdkapm/v1/model/business_topo_request.py
huaweicloudsdkapm/v1/model/change_agent_status_request.py
huaweicloudsdkapm/v1/model/change_agent_status_response.py
huaweicloudsdkapm/v1/model/client_span_info.py
huaweicloudsdkapm/v1/model/cmdb_tag_entity.py
huaweicloudsdkapm/v1/model/collector_category_info.py
huaweicloudsdkapm/v1/model/collector_config_model.py
huaweicloudsdkapm/v1/model/config_item.py
huaweicloudsdkapm/v1/model/config_item_override.py
huaweicloudsdkapm/v1/model/config_item_value.py
huaweicloudsdkapm/v1/model/create_ak_sk_request.py
huaweicloudsdkapm/v1/model/create_ak_sk_response.py
huaweicloudsdkapm/v1/model/create_aksk_model.py
huaweicloudsdkapm/v1/model/create_business_model.py
huaweicloudsdkapm/v1/model/create_business_request.py
huaweicloudsdkapm/v1/model/create_business_response.py
huaweicloudsdkapm/v1/model/delete_agent_request.py
huaweicloudsdkapm/v1/model/delete_agent_response.py
huaweicloudsdkapm/v1/model/delete_ak_sk_request.py
huaweicloudsdkapm/v1/model/delete_ak_sk_response.py
huaweicloudsdkapm/v1/model/delete_app_request.py
huaweicloudsdkapm/v1/model/delete_app_response.py
huaweicloudsdkapm/v1/model/detail_view_config_model.py
huaweicloudsdkapm-3.1.184.dist-info/METADATA
huaweicloudsdkapm-3.1.184.dist-info/WHEEL
huaweicloudsdkapm-3.1.184.dist-info/licenses/LICENSE
huaweicloudsdkapm-3.1.184.dist-info/RECORD
